{"guide_start.md":"73063b28","guide_vue2_alias.md":"8e3eac08","guide_vue2_axios.md":"3e1f1726","guide_vue2_base.md":"464b144c","guide_vue2_bundle.md":"d9d24eef","guide_vue2_chunks.md":"0a3d1312","guide_other_index.md":"24383439","guide_vue2_lint.md":"bcdbf636","guide_vue2_sass.md":"0540c1bd","guide_vue2_start.md":"50e4a44d","guide_edit.md":"2f737706","guide_vue2_env.md":"6e6e570e","guide_vue2_externals.md":"81bec8dc","guide_vue2_ie.md":"bf16d405","guide_vue3_env.md":"15c44b72","guide_vue3_i18n.md":"efcc4870","guide_vue3_lint.md":"c956f53d","guide_vue3_pinia.md":"f90c3d06","guide_vue3_proxy.md":"15dd8725","guide_vue3_router.md":"f8e4c12f","guide_vue3_start.md":"1d5e24be","guide_vue3_ui.md":"6b9ab25c","guide_vue3_viewport.md":"25648aaa","guide_vue3_vite.md":"52761283","index.md":"87fecdd2","guide_index.md":"8916baf2","guide_vue2_console.md":"d624aac3","guide_vue2_rem.md":"dc03687e","guide_vue2_vant.md":"7f5e95c2","guide_vue3_alias.md":"5df8d842","guide_vue2_proxy.md":"e19a725e","guide_vue3_axios.md":"9929e968","guide_vue2_vw.md":"2e9f914f","guide_vue3_base.md":"22bdbcc7","guide_about_index.md":"253c741c","guide_vue2_vuex.md":"ac525cdf","guide_vue2_router.md":"b749e959"}
